{
    "joint_Pelvis_01": "Bone",
    "joint_HipMaster_01": "Bone.001",
    "joint_HipLT_01": "Bone.002",
    "joint_KneeLT_01": "Bone.003",
    "joint_FootLT_01": "Bone.004",
    "joint_ToeLT_01": "Bone.005",
    "joint_HipRT_01": "Bone.006",
    "joint_KneeRT_01": "Bone.007",
    "joint_FootRT_01": "Bone.008",
    "joint_ToeRT_01": "Bone.009",
    "joint_PlateA_01": "Bone.010",
    "joint_PlateALT_01": "Bone.011",
    "joint_PlateART_01": "Bone.012",
    "joint_TorsoA_01": "Bone.013",
    "joint_TorsoB_01": "Bone.014",
    "joint_ClavicleLT_01": "Bone.015",
    "joint_ShoulderLT_01": "Bone.016",
    "joint_ElbowLT_01": "Bone.017",
    "joint_HandLT_01": "Bone.018",
    "joint_WeaponLT_01": "Bone.019",
    "joint_ThumbALT_01": "Bone.020",
    "joint_ThumbBLT_01": "Bone.021",
    "joint_ThumbCLT_01": "Bone.022",
    "joint_IndexALT_01": "Bone.023",
    "joint_IndexBLT_01": "Bone.024",
    "joint_IndexCLT_01": "Bone.025",
    "joint_FingerALT_01": "Bone.026",
    "joint_FingerBLT_01": "Bone.027",
    "joint_FingerCLT_01": "Bone.028",
    "joint_RingALT_01": "Bone.029",
    "joint_RingBLT_01": "Bone.030",
    "joint_RingCLT_01": "Bone.031",
    "joint_PinkyALT_01": "Bone.032",
    "joint_PinkyBLT_01": "Bone.033",
    "joint_PinkyCLT_01": "Bone.034",
    "joint_ShoulderPadALT_01": "Bone.035",
    "joint_ClavicleRT_01": "Bone.036",
    "joint_ShoulderRT_01": "Bone.037",
    "joint_ElbowRT_01": "Bone.038",
    "joint_HandRT_01": "Bone.039",
    "joint_WeaponRT_01": "Bone.040",
    "joint_LeftHandOffset": "Bone.041",
    "joint_ThumbART_01": "Bone.042",
    "joint_ThumbBRT_01": "Bone.043",
    "joint_ThumbCRT_01": "Bone.044",
    "joint_IndexART_01": "Bone.045",
    "joint_IndexBRT_01": "Bone.046",
    "joint_IndexCRT_01": "Bone.047",
    "joint_FingerART_01": "Bone.048",
    "joint_FingerBRT_01": "Bone.049",
    "joint_FingerCRT_01": "Bone.050",
    "joint_RingART_01": "Bone.051",
    "joint_RingBRT_01": "Bone.052",
    "joint_RingCRT_01": "Bone.053",
    "joint_PinkyART_01": "Bone.054",
    "joint_PinkyBRT_01": "Bone.055",
    "joint_PinkyCRT_01": "Bone.056",
    "joint_ShoulderPadART_01": "Bone.057",
    "joint_NeckA_01": "Bone.058",
    "joint_Head_01": "Bone.059",
    "joint_HandLT_IK": "Bone.060",
    "joint_HandRT_IK": "Bone.061",
    "joint_FootRT_IK": "Bone.062",
    "joint_FootLT_IK": "Bone.063"
}