[
    {
        "path": "Blueprint /Game/PROPS/Gameplay/BP_PROP_Container_01.BP_PROP_Container_01",
        "transform": {
            "loc": [
                25158.529296875,
                72495.0234375,
                -61350.9296875
            ],
            "rot": [
                0.0,
                0.0,
                59.06114959716797
            ],
            "scale": [
                1.0,
                1.0,
                1.0
            ]
        }
    },
    {
        "path": "Blueprint /Game/PROPS/Gameplay/BP_PROP_Container_01.BP_PROP_Container_01",
        "transform": {
            "loc": [
                23829.125,
                72624.96875,
                -61350.9296875
            ],
            "rot": [
                0.0,
                0.0,
                59.06114959716797
            ],
            "scale": [
                1.0,
                1.0,
                1.0
            ]
        }
    },
    {
        "path": "Blueprint /Game/PROPS/Gameplay/BP_PROP_Container_01.BP_PROP_Container_01",
        "transform": {
            "loc": [
                24850.8515625,
                72003.2265625,
                -61349.9296875
            ],
            "rot": [
                0.0,
                0.0,
                59.06114959716797
            ],
            "scale": [
                1.0,
                1.0,
                1.0
            ]
        }
    },
    {
        "path": "Blueprint /Game/PROPS/Gameplay/BP_PROP_Container_01.BP_PROP_Container_01",
        "transform": {
            "loc": [
                23517.783203125,
                72113.25,
                -60774.1328125
            ],
            "rot": [
                0.0,
                0.0,
                59.06114959716797
            ],
            "scale": [
                1.0,
                1.0,
                1.0
            ]
        }
    },
    {
        "path": "Blueprint /Game/PROPS/Gameplay/BP_PROP_Container_01.BP_PROP_Container_01",
        "transform": {
            "loc": [
                24546.0390625,
                71496.296875,
                -60774.1328125
            ],
            "rot": [
                0.0,
                0.0,
                59.06114959716797
            ],
            "scale": [
                1.0,
                1.0,
                1.0
            ]
        }
    },
    {
        "path": "Blueprint /Game/PROPS/Gameplay/BP_PROP_Container_01.BP_PROP_Container_01",
        "transform": {
            "loc": [
                23221.099609375,
                71618.359375,
                -61350.9296875
            ],
            "rot": [
                0.0,
                0.0,
                59.06114959716797
            ],
            "scale": [
                1.0,
                1.0,
                1.0
            ]
        }
    },
    {
        "path": "Blueprint /Game/PROPS/Gameplay/BP_PROP_Container_01.BP_PROP_Container_01",
        "transform": {
            "loc": [
                24250.359375,
                71001.421875,
                -61350.9296875
            ],
            "rot": [
                0.0,
                0.0,
                59.06114959716797
            ],
            "scale": [
                1.0,
                1.0,
                1.0
            ]
        }
    },
    {
        "path": "Blueprint /Game/PROPS/Gameplay/BP_PROP_Container_01.BP_PROP_Container_01",
        "transform": {
            "loc": [
                23220.099609375,
                71618.359375,
                -60774.1328125
            ],
            "rot": [
                0.0,
                0.0,
                59.06114959716797
            ],
            "scale": [
                1.0,
                1.0,
                1.0
            ]
        }
    },
    {
        "path": "Blueprint /Game/PROPS/Gameplay/BP_PROP_Container_01.BP_PROP_Container_01",
        "transform": {
            "loc": [
                24249.359375,
                71001.421875,
                -60774.1328125
            ],
            "rot": [
                0.0,
                0.0,
                59.06114959716797
            ],
            "scale": [
                1.0,
                1.0,
                1.0
            ]
        }
    },
    {
        "path": "Blueprint /Game/PROPS/Ambiance/BP_SM_XX_PROP_AMB_Crate_01.BP_SM_XX_PROP_AMB_Crate_01",
        "transform": {
            "loc": [
                26913.17578125,
                72487.46875,
                -60751.12890625
            ],
            "rot": [
                0.0,
                0.0,
                -30.937572479248047
            ],
            "scale": [
                1.0,
                1.0,
                1.0
            ]
        }
    },
    {
        "path": "Blueprint /Game/PROPS/Ambiance/BP_SM_XX_PROP_AMB_Crate_01.BP_SM_XX_PROP_AMB_Crate_01",
        "transform": {
            "loc": [
                26746.87890625,
                72671.078125,
                -60751.0
            ],
            "rot": [
                0.0,
                0.0,
                -120.93750762939453
            ],
            "scale": [
                1.0,
                1.0,
                1.0
            ]
        }
    },
    {
        "path": "Blueprint /Game/PROPS/Ambiance/BP_SM_XX_PROP_AMB_Crate_01.BP_SM_XX_PROP_AMB_Crate_01",
        "transform": {
            "loc": [
                26746.87890625,
                72671.078125,
                -60600.0
            ],
            "rot": [
                0.0,
                0.0,
                -120.93750762939453
            ],
            "scale": [
                1.0,
                1.0,
                1.0
            ]
        }
    },
    {
        "path": "Blueprint /Game/PROPS/Ambiance/BP_SM_XX_PROP_AMB_Crate_01.BP_SM_XX_PROP_AMB_Crate_01",
        "transform": {
            "loc": [
                26913.17578125,
                72487.46875,
                -60594.0
            ],
            "rot": [
                0.0,
                0.0,
                -25.311988830566406
            ],
            "scale": [
                1.0,
                1.0,
                1.0
            ]
        }
    },
    {
        "path": "Blueprint /Game/PROPS/Ambiance/BP_SM_XX_PROP_AMB_Crate_01.BP_SM_XX_PROP_AMB_Crate_01",
        "transform": {
            "loc": [
                26894.77734375,
                72933.375,
                -60751.0
            ],
            "rot": [
                0.0,
                0.0,
                -115.31243896484375
            ],
            "scale": [
                1.0,
                1.0,
                1.0
            ]
        }
    },
    {
        "path": "Blueprint /Game/PROPS/Ambiance/BP_SM_XX_PROP_AMB_Crate_01.BP_SM_XX_PROP_AMB_Crate_01",
        "transform": {
            "loc": [
                26908.3828125,
                72940.375,
                -60600.0
            ],
            "rot": [
                0.0,
                0.0,
                -120.93750762939453
            ],
            "scale": [
                1.0,
                1.0,
                1.0
            ]
        }
    },
    {
        "path": "StaticMesh /Game/PROPS/Gameplay/SM_PROP_Container_01.SM_PROP_Container_01",
        "transform": {
            "loc": [
                23569.5390625,
                73758.90625,
                -60783.0
            ],
            "rot": [
                0.0,
                0.0,
                -177.18748474121094
            ],
            "scale": [
                1.0,
                1.0,
                1.0
            ]
        }
    },
    {
        "path": "StaticMesh /Game/PROPS/Gameplay/SM_PROP_Container_01.SM_PROP_Container_01",
        "transform": {
            "loc": [
                26503.380859375,
                74423.96875,
                -60769.0
            ],
            "rot": [
                0.0,
                0.0,
                -120.93719482421875
            ],
            "scale": [
                1.0,
                1.0,
                1.0
            ]
        }
    },
    {
        "path": "StaticMesh /Game/PROPS/Gameplay/SM_PROP_Container_01.SM_PROP_Container_01",
        "transform": {
            "loc": [
                24557.794921875,
                71505.3125,
                -61351.0
            ],
            "rot": [
                0.0,
                0.0,
                -120.9373550415039
            ],
            "scale": [
                1.0,
                1.0,
                1.0
            ]
        }
    },
    {
        "path": "StaticMesh /Game/PROPS/Gameplay/SM_PROP_Container_01.SM_PROP_Container_01",
        "transform": {
            "loc": [
                23531.23828125,
                72128.78125,
                -61351.0
            ],
            "rot": [
                0.0,
                0.0,
                -120.9373550415039
            ],
            "scale": [
                1.0,
                1.0,
                1.0
            ]
        }
    },
    {
        "path": "StaticMesh /Game/PROPS/Gameplay/DefenseWalls/SM_XX_PROP_GAM_Straight_SandBag01.SM_XX_PROP_GAM_Straight_SandBag01",
        "transform": {
            "loc": [
                25668.978515625,
                72242.0,
                -60794.0
            ],
            "rot": [
                0.0,
                0.0,
                149.0626678466797
            ],
            "scale": [
                0.75,
                1.0,
                1.0
            ]
        }
    },
    {
        "path": "StaticMesh /Game/PROPS/Gameplay/DefenseWalls/SM_XX_PROP_GAM_Straight_SandBag02.SM_XX_PROP_GAM_Straight_SandBag02",
        "transform": {
            "loc": [
                25493.298828125,
                71951.234375,
                -60801.0
            ],
            "rot": [
                0.0,
                0.0,
                -30.93745994567871
            ],
            "scale": [
                0.75,
                1.0,
                1.0
            ]
        }
    },
    {
        "path": "StaticMesh /Game/PROPS/Gameplay/DefenseWalls/SM_XX_PROP_GAM_Straight_SandBag01.SM_XX_PROP_GAM_Straight_SandBag01",
        "transform": {
            "loc": [
                27160.373046875,
                72530.328125,
                -60766.0
            ],
            "rot": [
                0.0,
                0.0,
                -28.125
            ],
            "scale": [
                0.75,
                1.0,
                1.0
            ]
        }
    },
    {
        "path": "StaticMesh /Game/PROPS/Gameplay/DefenseWalls/SM_XX_PROP_GAM_Straight_SandBag01.SM_XX_PROP_GAM_Straight_SandBag01",
        "transform": {
            "loc": [
                27452.1796875,
                73076.21875,
                -60766.0
            ],
            "rot": [
                0.0,
                0.0,
                -28.125
            ],
            "scale": [
                0.75,
                1.0,
                1.0
            ]
        }
    },
    {
        "path": "StaticMesh /Game/PROPS/Gameplay/DefenseWalls/SM_XX_PROP_GAM_Straight_SandBag02.SM_XX_PROP_GAM_Straight_SandBag02",
        "transform": {
            "loc": [
                27304.25390625,
                72808.328125,
                -60763.0
            ],
            "rot": [
                0.0,
                0.0,
                151.87509155273438
            ],
            "scale": [
                0.75,
                1.0,
                1.0
            ]
        }
    },
    {
        "path": "StaticMesh /Game/PROPS/Gameplay/DefenseWalls/SM_XX_PROP_GAM_Straight_SandBag01.SM_XX_PROP_GAM_Straight_SandBag01",
        "transform": {
            "loc": [
                25323.271484375,
                71663.40625,
                -60794.0
            ],
            "rot": [
                0.0,
                0.0,
                149.0626678466797
            ],
            "scale": [
                0.75,
                1.0,
                1.0
            ]
        }
    }
]